setup.py
confyg/__init__.py
confyg/transformations.py
confyg.egg-info/PKG-INFO
confyg.egg-info/SOURCES.txt
confyg.egg-info/dependency_links.txt
confyg.egg-info/top_level.txt