Metadata-Version: 1.0
Name: confyg
Version: 0.2.0.0
Summary: Class based configuration.
Home-page: https://github.com/wilbertom/confyg
Author: Wilberto Morales
Author-email: wilbertomorales777@gmail.com
License: MIT
Platform: UNKNOWN
